outlierRemoval_python/outlierRemoval.py
outlierRemoval_kjindal_101703299-1.0.2.dist-info/LICENSE.txt
outlierRemoval_kjindal_101703299-1.0.2.dist-info/METADATA
outlierRemoval_kjindal_101703299-1.0.2.dist-info/WHEEL
outlierRemoval_kjindal_101703299-1.0.2.dist-info/entry_points.txt
outlierRemoval_kjindal_101703299-1.0.2.dist-info/top_level.txt
outlierRemoval_kjindal_101703299-1.0.2.dist-info/RECORD
